pyramid_rpc/__init__.py
pyramid_rpc/amfgateway.py
pyramid_rpc/compat.py
pyramid_rpc/jsonrpc.py
pyramid_rpc/mapper.py
pyramid_rpc/util.py
pyramid_rpc/xmlrpc.py
pyramid_rpc/tests/__init__.py
pyramid_rpc/tests/test_amfgateway.py
pyramid_rpc/tests/test_jsonrpc.py
pyramid_rpc/tests/test_mapper.py
pyramid_rpc/tests/test_simplerpc.py
pyramid_rpc/tests/test_xmlrpc.py
pyramid_rpc/tests/fixtures/__init__.py
pyramid_rpc/tests/fixtures/simplerpc.py
pyramid_rpc-0.8.dist-info/DESCRIPTION.rst
pyramid_rpc-0.8.dist-info/METADATA
pyramid_rpc-0.8.dist-info/RECORD
pyramid_rpc-0.8.dist-info/WHEEL
pyramid_rpc-0.8.dist-info/metadata.json
pyramid_rpc-0.8.dist-info/top_level.txt
