Metadata-Version: 2.0
Name: pyramid-rpc
Version: 0.8
Summary: RPC support for the Pyramid web framework
Home-page: http://docs.pylonsproject.org/projects/pyramid_rpc/en/latest/
Author: Michael Merickel
Author-email: michael@merickel.org
License: BSD-derived (http://www.repoze.org/LICENSE.txt)
Keywords: web wsgi pyramid pylons xml-rpc json-rpc amf
Platform: UNKNOWN
Classifier: Intended Audience :: Developers
Classifier: Programming Language :: Python
Classifier: Programming Language :: Python :: 2
Classifier: Programming Language :: Python :: 3
Classifier: Programming Language :: Python :: 2.7
Classifier: Programming Language :: Python :: 3.3
Classifier: Programming Language :: Python :: 3.4
Classifier: Programming Language :: Python :: 3.5
Classifier: Framework :: Pyramid
Requires-Dist: pyramid (>=1.4)
Requires-Dist: venusian (>=1.0a7)
Provides-Extra: amf
Requires-Dist: pyamf; extra == 'amf'
Provides-Extra: docs
Requires-Dist: Sphinx (>=1.3.1); extra == 'docs'
Requires-Dist: pylons-sphinx-themes; extra == 'docs'
Provides-Extra: testing
Requires-Dist: WebTest; extra == 'testing'
Requires-Dist: coverage; extra == 'testing'
Requires-Dist: nose; extra == 'testing'
Requires-Dist: pyramid (>=1.4); extra == 'testing'
Requires-Dist: venusian (>=1.0a7); extra == 'testing'
